voltron/__init__.py
voltron/__main__.py
voltron/api.py
voltron/colour.py
voltron/core.py
voltron/dbg.py
voltron/entry.py
voltron/lexers.py
voltron/main.py
voltron/plugin.py
voltron/rdb.py
voltron/repl.py
voltron/styles.py
voltron/view.py
voltron/config/default.cfg
voltron/plugins/__init__.py
voltron/plugins/api/__init__.py
voltron/plugins/api/backtrace.py
voltron/plugins/api/breakpoints.py
voltron/plugins/api/command.py
voltron/plugins/api/dereference.py
voltron/plugins/api/disassemble.py
voltron/plugins/api/memory.py
voltron/plugins/api/plugins.py
voltron/plugins/api/registers.py
voltron/plugins/api/stack.py
voltron/plugins/api/state.py
voltron/plugins/api/targets.py
voltron/plugins/api/version.py
voltron/plugins/command/__init__.py
voltron/plugins/command/var.py
voltron/plugins/debugger/__init__.py
voltron/plugins/debugger/dbg_gdb.py
voltron/plugins/debugger/dbg_lldb.py
voltron/plugins/debugger/dbg_mock.py
voltron/plugins/debugger/dbg_vdb.py
voltron/plugins/debugger/dbg_windbg.py
voltron/plugins/view/__init__.py
voltron/plugins/view/backtrace.py
voltron/plugins/view/breakpoints.py
voltron/plugins/view/command.py
voltron/plugins/view/disasm.py
voltron/plugins/view/memory.py
voltron/plugins/view/register.py
voltron-0.1.7.dist-info/DESCRIPTION.rst
voltron-0.1.7.dist-info/METADATA
voltron-0.1.7.dist-info/RECORD
voltron-0.1.7.dist-info/WHEEL
voltron-0.1.7.dist-info/entry_points.txt
voltron-0.1.7.dist-info/metadata.json
voltron-0.1.7.dist-info/top_level.txt
