Metadata-Version: 2.0
Name: voltron
Version: 0.1.7
Summary: A debugger UI
Home-page: https://github.com/snare/voltron
Author: snare
Author-email: snare@ho.ax
License: MIT
Keywords: voltron debugger ui gdb lldb vdb vivisect vtrace windbg cdb pykd
Platform: UNKNOWN
Requires-Dist: blessed
Requires-Dist: flask
Requires-Dist: flask-restful
Requires-Dist: pygments
Requires-Dist: pygments
Requires-Dist: pysigset
Requires-Dist: requests
Requires-Dist: requests-unixsocket
Requires-Dist: scruffington (>=0.3.6)
Requires-Dist: six
